cli.py
henosis_cli_tools/__init__.py
henosis_cli_tools/cli_entry.py
henosis_cli_tools/input_engine.py
henosis_cli_tools/settings_ui.py
henosis_cli_tools/tool_impl.py
henosis_cli-0.6.9.dist-info/METADATA
henosis_cli-0.6.9.dist-info/WHEEL
henosis_cli-0.6.9.dist-info/entry_points.txt
henosis_cli-0.6.9.dist-info/top_level.txt
henosis_cli-0.6.9.dist-info/RECORD
