Metadata-Version: 2.4
Name: henosis-cli
Version: 0.6.9
Summary: henosis-cli — interactive CLI for the Henosis multi-provider streaming chat backend, with optional local tools.
Author-email: henosis <henosis@henosis.us>
License-Expression: LicenseRef-Proprietary
Project-URL: Homepage, https://henosis.us
Project-URL: Contact, https://henosis.us/contact
Keywords: henosis,tools,filesystem,sandbox,patch,subprocess,cli
Classifier: Programming Language :: Python :: 3
Classifier: Programming Language :: Python :: 3 :: Only
Classifier: Operating System :: OS Independent
Classifier: Environment :: Console
Classifier: Topic :: Utilities
Classifier: Intended Audience :: Developers
Requires-Python: >=3.9
Requires-Dist: httpx>=0.28.1
Requires-Dist: packaging>=24.0
Requires-Dist: rich>=14.1.0
Requires-Dist: prompt_toolkit>=3.0.52
Requires-Dist: websockets>=11.0.0
